swagger_ui_gentok/__init__.py
swagger_ui_gentok/core.py
swagger_ui_gentok/utils.py
swagger_ui_gentok_diy-0.0.2.dist-info/METADATA
swagger_ui_gentok_diy-0.0.2.dist-info/WHEEL
swagger_ui_gentok_diy-0.0.2.dist-info/licence.txt
swagger_ui_gentok_diy-0.0.2.dist-info/top_level.txt
swagger_ui_gentok_diy-0.0.2.dist-info/RECORD
