Metadata-Version: 2.1
Name: swagger-ui-gentok-diy
Version: 0.0.2
Summary: Swagger DIY for gentok
Home-page: UNKNOWN
Author: KDH
Author-email: dongha0144@naver.com
License: MIT
Platform: UNKNOWN
Requires-Python: >=3
License-File: licence.txt
